pvfit/__init__.py
pvfit/__init___test.py
pvfit/common.py
pvfit/common_test.py
pvfit/types.py
pvfit/measurement/__init__.py
pvfit/measurement/__init___test.py
pvfit/measurement/iv/__init__.py
pvfit/measurement/iv/__init___test.py
pvfit/measurement/iv/computation.py
pvfit/measurement/iv/computation_test.py
pvfit/measurement/iv/types.py
pvfit/measurement/spectral_correction/README.md
pvfit/measurement/spectral_correction/__init__.py
pvfit/measurement/spectral_correction/__init___test.py
pvfit/measurement/spectral_correction/computation.py
pvfit/measurement/spectral_correction/computation_test.py
pvfit/measurement/spectral_correction/spectra.py
pvfit/measurement/spectral_correction/spectra_test.py
pvfit/measurement/spectral_correction/types.py
pvfit/measurement/spectral_correction/types_test.py
pvfit/measurement/spectral_correction/demos/__init__.py
pvfit/measurement/spectral_correction/demos/data.py
pvfit/measurement/spectral_correction/demos/data_test.py
pvfit/measurement/spectral_correction/demos/getting_started.py
pvfit/measurement/spectral_correction/demos/getting_started_test.py
pvfit/modeling/__init__.py
pvfit/modeling/__init___test.py
pvfit/modeling/ac/__init__.py
pvfit/modeling/ac/__init___test.py
pvfit/modeling/ac/sipm/__init__.py
pvfit/modeling/ac/sipm/__init___test.py
pvfit/modeling/ac/sipm/inference.py
pvfit/modeling/ac/sipm/inference_test.py
pvfit/modeling/ac/sipm/simulation.py
pvfit/modeling/ac/sipm/simulation_test.py
pvfit/modeling/dc/__init__.py
pvfit/modeling/dc/__init___test.py
pvfit/modeling/dc/common.py
pvfit/modeling/dc/common_test.py
pvfit/modeling/dc/single_diode/__init__.py
pvfit/modeling/dc/single_diode/__init___test.py
pvfit/modeling/dc/single_diode/equation/__init__.py
pvfit/modeling/dc/single_diode/equation/__init___test.py
pvfit/modeling/dc/single_diode/equation/demos/__init__.py
pvfit/modeling/dc/single_diode/equation/demos/__init___test.py
pvfit/modeling/dc/single_diode/equation/demos/getting_started.py
pvfit-0.0.1.dist-info/LICENSE
pvfit-0.0.1.dist-info/METADATA
pvfit-0.0.1.dist-info/WHEEL
pvfit-0.0.1.dist-info/top_level.txt
pvfit-0.0.1.dist-info/RECORD
