Metadata-Version: 2.1
Name: pvfit
Version: 0.0.1
Summary: PVfit: Photovoltaic (PV) Device Performance Measurement and Modeling
Author-email: Mark Campanelli <mark.campanelli@gmail.com>
License: MIT License
Project-URL: Source, https://github.com/markcampanelli/pvfit
Project-URL: BugReports, https://github.com/markcampanelli/pvfit/issues
Project-URL: Developer, https://intelligentmeasurementsystems.com
Project-URL: Discussions, https://github.com/markcampanelli/pvfit/discussions
Project-URL: PullRequests, https://github.com/markcampanelli/pvfit/pulls
Project-URL: WebApplication, https://pvfit.app
Keywords: PV,measurement,modeling,photovoltaic,simulation,solar
Classifier: Development Status :: 3 - Alpha
Classifier: Intended Audience :: Developers
Classifier: Intended Audience :: Education
Classifier: Intended Audience :: End Users/Desktop
Classifier: Intended Audience :: Science/Research
Classifier: Natural Language :: English
Classifier: Topic :: Scientific/Engineering
Classifier: Topic :: Software Development :: Libraries
Classifier: License :: OSI Approved :: MIT License
Classifier: Programming Language :: Python :: 3
Classifier: Programming Language :: Python :: 3.10
Classifier: Programming Language :: Python :: 3.11
Classifier: Programming Language :: Python :: 3.12
Requires-Python: <3.13,>=3.10
License-File: LICENSE
Requires-Dist: numpy <2,>=1.17.3
Requires-Dist: scipy <2,>=1.5
Provides-Extra: demo
Requires-Dist: matplotlib <3.8,>=3 ; extra == 'demo'
Requires-Dist: pandas <3,>=2 ; extra == 'demo'
Requires-Dist: pvlib <0.11,>=0.10.3 ; extra == 'demo'
Provides-Extra: dev
Requires-Dist: build <2,>=1.2.1 ; extra == 'dev'
Requires-Dist: black <25,>=24 ; extra == 'dev'
Requires-Dist: check-manifest <0.50,>=0.49 ; extra == 'dev'
Requires-Dist: pylint <3,>=2 ; extra == 'dev'
Provides-Extra: docs
Requires-Dist: sphinx <5,>=4 ; extra == 'docs'
Requires-Dist: sphinx-rtd-theme <2,>=1 ; extra == 'docs'
Provides-Extra: test
Requires-Dist: pandas <3,>=2 ; extra == 'test'
Requires-Dist: pytest <8,>=7 ; extra == 'test'
Requires-Dist: pytest-cov <5,>=4 ; extra == 'test'
